README.md
setup.cfg
setup.py
jh_jwt/__init__.py
jh_jwt/jh_jwt.py
jh_jwt.egg-info/PKG-INFO
jh_jwt.egg-info/SOURCES.txt
jh_jwt.egg-info/dependency_links.txt
jh_jwt.egg-info/requires.txt
jh_jwt.egg-info/top_level.txt