Metadata-Version: 1.0
Name: jh-jwt
Version: 0.0.2
Summary: JSONWebToken Authenticator for JupyterHub
Home-page: https://github.com/jpetrucciani/jh_jwt
Author: mogthesprog, jpetrucciani
Author-email: mevanj89@gmail.com, jacobi@mimirhq.com
License: Apache 2.0
Platform: UNKNOWN
